atlas_s3_hook/Exceptions.py
atlas_s3_hook/S3Hook.py
atlas_s3_hook/S3MetadataClient.py
atlas_s3_hook/S3PathClass.py
atlas_s3_hook/S3PathType.py
atlas_s3_hook/S3Scanner.py
atlas_s3_hook/__init__.py
atlass3hook-0.0.3.dist-info/LICENSE
atlass3hook-0.0.3.dist-info/METADATA
atlass3hook-0.0.3.dist-info/WHEEL
atlass3hook-0.0.3.dist-info/top_level.txt
atlass3hook-0.0.3.dist-info/RECORD
