Metadata-Version: 2.1
Name: atlass3hook
Version: 0.0.3
Summary: This atlas s3 hook uses s3fs package to gather the metadata of bucket, pseudo_dir and object, then it inserts these metadata into Atlas instances.
Home-page: https://git.lab.sspcloud.fr/pengfei/atlass3hook
Author: Pengfei Liu
Author-email: pengfei.liu@insee.fr
License: Apache License 2.0
Platform: UNKNOWN
Classifier: Programming Language :: Python :: 3
Classifier: License :: OSI Approved :: Apache Software License
Classifier: Operating System :: OS Independent
Requires-Python: >=3.7
Requires-Dist: s3fs (>=0.5.0)
Requires-Dist: atlaspyapi (>=0.1.9)
